datadog/__init__.py
datadog/py.typed
datadog/version.py
datadog/api/__init__.py
datadog/api/api_client.py
datadog/api/aws_integration.py
datadog/api/aws_log_integration.py
datadog/api/azure_integration.py
datadog/api/comments.py
datadog/api/constants.py
datadog/api/dashboard_list_v2.py
datadog/api/dashboard_lists.py
datadog/api/dashboards.py
datadog/api/distributions.py
datadog/api/downtimes.py
datadog/api/events.py
datadog/api/exceptions.py
datadog/api/format.py
datadog/api/gcp_integration.py
datadog/api/graphs.py
datadog/api/hosts.py
datadog/api/http_client.py
datadog/api/infrastructure.py
datadog/api/logs.py
datadog/api/metadata.py
datadog/api/metrics.py
datadog/api/monitors.py
datadog/api/permissions.py
datadog/api/resources.py
datadog/api/roles.py
datadog/api/screenboards.py
datadog/api/service_checks.py
datadog/api/service_level_objectives.py
datadog/api/synthetics.py
datadog/api/tags.py
datadog/api/timeboards.py
datadog/api/users.py
datadog/dogshell/__init__.py
datadog/dogshell/comment.py
datadog/dogshell/common.py
datadog/dogshell/dashboard.py
datadog/dogshell/dashboard_list.py
datadog/dogshell/downtime.py
datadog/dogshell/event.py
datadog/dogshell/host.py
datadog/dogshell/metric.py
datadog/dogshell/monitor.py
datadog/dogshell/screenboard.py
datadog/dogshell/search.py
datadog/dogshell/service_check.py
datadog/dogshell/service_level_objective.py
datadog/dogshell/tag.py
datadog/dogshell/timeboard.py
datadog/dogshell/wrap.py
datadog/dogstatsd/__init__.py
datadog/dogstatsd/aggregator.py
datadog/dogstatsd/base.py
datadog/dogstatsd/container.py
datadog/dogstatsd/context.py
datadog/dogstatsd/context_async.py
datadog/dogstatsd/metric_types.py
datadog/dogstatsd/metrics.py
datadog/dogstatsd/route.py
datadog/threadstats/__init__.py
datadog/threadstats/aws_lambda.py
datadog/threadstats/base.py
datadog/threadstats/constants.py
datadog/threadstats/events.py
datadog/threadstats/metrics.py
datadog/threadstats/periodic_timer.py
datadog/threadstats/reporters.py
datadog-0.50.1.dist-info/METADATA
datadog-0.50.1.dist-info/WHEEL
datadog-0.50.1.dist-info/entry_points.txt
datadog-0.50.1.dist-info/licenses/LICENSE
datadog-0.50.1.dist-info/licenses/LICENSE-3rdparty.csv
datadog-0.50.1.dist-info/RECORD
