Metadata-Version: 2.3
Name: datadog
Version: 0.50.1
Summary: The Datadog Python library
Project-URL: Bug Tracker, https://github.com/DataDog/datadogpy/issues
Project-URL: Documentation, https://datadogpy.readthedocs.io/en/latest/
Project-URL: Source Code, https://github.com/DataDog/datadogpy
Author-email: "Datadog, Inc." <dev@datadoghq.com>
License: BSD-3-Clause
License-File: LICENSE
License-File: LICENSE-3rdparty.csv
Keywords: datadog
Classifier: License :: OSI Approved :: BSD License
Classifier: Operating System :: OS Independent
Classifier: Programming Language :: Python :: 2.7
Classifier: Programming Language :: Python :: 3.7
Classifier: Programming Language :: Python :: 3.8
Classifier: Programming Language :: Python :: 3.9
Classifier: Programming Language :: Python :: Implementation :: CPython
Classifier: Programming Language :: Python :: Implementation :: PyPy
Requires-Python: !=3.0.*,!=3.1.*,!=3.2.*,!=3.3.*,!=3.4.*,!=3.5.*,!=3.6.*,>=2.7
Requires-Dist: configparser<5; python_version < '3.0'
Requires-Dist: requests>=2.6.0
Requires-Dist: typing; python_version < '3.5'
